HtmlFileWriter-0.2.data/data/src/html_writer.py/html_writer.py
src/__init__.py
src/html_writer.py
HtmlFileWriter-0.2.dist-info/LICENCE
HtmlFileWriter-0.2.dist-info/METADATA
HtmlFileWriter-0.2.dist-info/WHEEL
HtmlFileWriter-0.2.dist-info/top_level.txt
HtmlFileWriter-0.2.dist-info/RECORD
