Metadata-Version: 2.1
Name: HtmlFileWriter
Version: 0.2
Summary: Sets up and writes an HTML File using a filewriter.
Author: kunaalg
Author-email: <kunaal@runcode.in>
Keywords: python,FileWriter,App,HTML,Function,math
Classifier: Development Status :: 4 - Beta
Classifier: Intended Audience :: Developers
Classifier: Programming Language :: Python :: 3
Classifier: Operating System :: Unix
Classifier: Operating System :: MacOS :: MacOS X
Classifier: Operating System :: Microsoft :: Windows
License-File: LICENCE
Requires-Dist: datetime
Requires-Dist: pandas
Requires-Dist: requests
Requires-Dist: virtualenv
